word2numberi18n/__init__.py
word2numberi18n/w2n.py
word2numberi18n/data/__init__.py
word2numberi18n/data/config_de.properties
word2numberi18n/data/config_en.properties
word2numberi18n/data/config_es.properties
word2numberi18n/data/config_fr.properties
word2numberi18n/data/config_hi.properties
word2numberi18n/data/config_pt.properties
word2numberi18n/data/config_ru.properties
word2numberi18n/data/config_sk.properties
word2number_i18n-1.2.0.dist-info/METADATA
word2number_i18n-1.2.0.dist-info/WHEEL
word2number_i18n-1.2.0.dist-info/top_level.txt
word2number_i18n-1.2.0.dist-info/RECORD
