Metadata-Version: 2.1
Name: word2number-i18n
Version: 1.2.0
Summary: Convert number words from different languages with Python, CSharp or Java API eg. three hundred and forty two to numbers (342) or vingt-et-un (21) or две целых три десятых (2.3).
Home-page: https://github.com/bastie/w2ni18n
Author: Sebastian Ritter
Author-email: bastie@users.noreply.github.com
License: UNKNOWN
Project-URL: Source, https://github.com/bastie/w2ni18n
Keywords: numbers,convert,words,i18n
Platform: UNKNOWN
Classifier: Intended Audience :: Developers
Classifier: Programming Language :: Python
Classifier: Development Status :: 5 - Production/Stable
Classifier: License :: OSI Approved :: MIT License
Classifier: Programming Language :: Python :: 3
Classifier: Topic :: Software Development :: Internationalization
Requires-Python: >=3
